README.md
setup.py
src/nyquist.egg-info/PKG-INFO
src/nyquist.egg-info/SOURCES.txt
src/nyquist.egg-info/dependency_links.txt
src/nyquist.egg-info/top_level.txt
src/nyquist/_private/__init__.py
src/nyquist/_private/assets/__init__.py
src/nyquist/_private/assets/resource_descriptions.py
src/nyquist/_private/network/__init__.py
src/nyquist/_private/network/base.py
src/nyquist/_private/network/http.py
src/nyquist/_private/network/ws.py
src/nyquist/control/__init__.py
src/nyquist/control/executor.py
src/nyquist/lab/__init__.py
src/nyquist/lab/client.py
src/nyquist/lab/descriptions.py