Metadata-Version: 2.1
Name: nyquist
Version: 0.2.3
Summary: A client for control-systems laboratories.
Home-page: http://packages.python.org/nyquist
Author: Marco Miretti
Author-email: marcomiretti@gmail.com
License: GPLv3
Keywords: control laboratories remote client http websockets
Platform: UNKNOWN
